sinhala_speech_to_text/__init__.py
sinhala_speech_to_text/sinhala_stt.py
sinhala_speech_to_text-1.0.1.dist-info/METADATA
sinhala_speech_to_text-1.0.1.dist-info/WHEEL
sinhala_speech_to_text-1.0.1.dist-info/top_level.txt
sinhala_speech_to_text-1.0.1.dist-info/RECORD
